{
  "questions": [
    {
      "level": 1,
      "question": "Põhimõiste (Agiilne tarkvaraarendus): Iteratsioonidega arendamine. Milline vastus on kõige täpsem?",
      "options": [
        "varane tagasiside",
        "aastane plaan lukus",
        "testid alles lõpus",
        "kood korraga valmis"
      ],
      "correctIndex": 0,
      "explanation": "Iteratsioonid annavad võimaluse tulemust vara kontrollida ja suunda parandada.",
      "hint": "Mõtle lühikesele tagasisidetsüklile."
    },
    {
      "level": 1,
      "question": "Põhimõiste (Agiilne tarkvaraarendus): Sprint review eesmärk. Milline vastus on kõige täpsem?",
      "options": [
        "arendaja süüdistamine",
        "valminud töö näitamine",
        "backlogi peitmine",
        "testide eemaldamine"
      ],
      "correctIndex": 1,
      "explanation": "Review näitab valmis inkrementi ja kogub tagasisidet.",
      "hint": "Mõtle demo ja tagasiside peale."
    },
    {
      "level": 1,
      "question": "Põhimõiste (Agiilne tarkvaraarendus): Kasutajaloo hea sõnastus. Milline vastus on kõige täpsem?",
      "options": [
        "Muuda faili rida 42",
        "Lisa sinine nupp",
        "Kasutajana tahan..., et...",
        "Installi pakett"
      ],
      "correctIndex": 2,
      "explanation": "Kasutajalugu kirjeldab vajadust ja põhjust, mitte ainult tehnilist käsku.",
      "hint": "Otsi kasutaja vaadet."
    },
    {
      "level": 1,
      "question": "Põhimõiste (Agiilne tarkvaraarendus): Definition of Done roll. Milline vastus on kõige täpsem?",
      "options": [
        "soovide nimekiri",
        "paroolide hoidla",
        "ainult disainifail",
        "valmiduse kontrollnimekiri"
      ],
      "correctIndex": 3,
      "explanation": "DoD teeb valmis töö kvaliteedinõuded kontrollitavaks.",
      "hint": "Mõtle, millal saab töö valmis lugeda."
    },
    {
      "level": 1,
      "question": "Põhimõiste (Agiilse tarkvaraarenduse projekt): Git branch projektitöös. Milline vastus on kõige täpsem?",
      "options": [
        "eraldab muudatused",
        "asendab testid",
        "lukustab maini",
        "kustutab ajaloo"
      ],
      "correctIndex": 0,
      "explanation": "Harus saab issue muudatusi arendada põhiharust eraldi.",
      "hint": "Mõtle paralleelsele tööle."
    },
    {
      "level": 1,
      "question": "Põhimõiste (Agiilse tarkvaraarenduse projekt): Pull requesti eesmärk. Milline vastus on kõige täpsem?",
      "options": [
        "paroolide jagamine",
        "muudatuste ülevaatus",
        "serveri restart",
        "CSS minimeerimine"
      ],
      "correctIndex": 1,
      "explanation": "PR koondab muudatused aruteluks, testimiseks ja review'ks.",
      "hint": "Mõtle teise silmapaarile."
    },
    {
      "level": 1,
      "question": "Põhimõiste (Agiilse tarkvaraarenduse projekt): Commit sõnum. Milline vastus on kõige täpsem?",
      "options": [
        "salasõnaga",
        "suvaline punkt",
        "lühike ja sisuline",
        "ainult emoji"
      ],
      "correctIndex": 2,
      "explanation": "Hea commit selgitab muudatuse eesmärki ja aitab ajalugu lugeda.",
      "hint": "Mõtle jälgitavusele."
    },
    {
      "level": 1,
      "question": "Põhimõiste (Agiilse tarkvaraarenduse projekt): Demo projektis. Milline vastus on kõige täpsem?",
      "options": [
        "näitab ainult failipuud",
        "asendab testid",
        "peidab poolelioleva töö",
        "näitab kasutajale väärtust"
      ],
      "correctIndex": 3,
      "explanation": "Demo peaks tõestama põhivoo töötamist kasutaja vaates.",
      "hint": "Mõtle valminud inkremendile."
    },
    {
      "level": 1,
      "question": "Põhimõiste (Andmebaaside alused): Relatsioonilise tabeli rida. Milline vastus on kõige täpsem?",
      "options": [
        "üks kirje",
        "üks andmebaasimootor",
        "CSS reegel",
        "HTTP päis"
      ],
      "correctIndex": 0,
      "explanation": "Rida esindab üht objekti või sündmust tabelis.",
      "hint": "Mõtle tabeli reale."
    },
    {
      "level": 1,
      "question": "Põhimõiste (Andmebaaside alused): Primaarvõti. Milline vastus on kõige täpsem?",
      "options": [
        "duplikaatnimi",
        "unikaalne identifikaator",
        "parool",
        "CSS klass"
      ],
      "correctIndex": 1,
      "explanation": "Primaarvõti eristab kirjeid ja sellele saab viidata.",
      "hint": "Mõtle üheselt tuvastamisele."
    },
    {
      "level": 1,
      "question": "Põhimõiste (Andmebaaside alused): Võõrvõti. Milline vastus on kõige täpsem?",
      "options": [
        "brauseri muutuja",
        "SQL kommentaar",
        "viide teise tabeli kirjele",
        "HTML vorm"
      ],
      "correctIndex": 2,
      "explanation": "Võõrvõti loob seose tabelite vahel.",
      "hint": "Mõtle kliendi ja tellimuse seosele."
    },
    {
      "level": 1,
      "question": "Põhimõiste (Andmebaaside alused): NULL andmebaasis. Milline vastus on kõige täpsem?",
      "options": [
        "väärtus on null number",
        "väli on alati vale",
        "tabel on tühi",
        "väärtus puudub"
      ],
      "correctIndex": 3,
      "explanation": "NULL tähendab teadmata või puuduvat väärtust, mitte tingimata arvu 0.",
      "hint": "Mõtle puudumisele."
    },
    {
      "level": 1,
      "question": "Põhimõiste (Andmebaaside projekteerimine): ERD eesmärk. Milline vastus on kõige täpsem?",
      "options": [
        "näidata olemeid ja seoseid",
        "kujundada nuppe",
        "käivitada server",
        "testida CSS-i"
      ],
      "correctIndex": 0,
      "explanation": "ERD aitab andmemudelit enne tabelite loomist läbi mõelda.",
      "hint": "Mõtle diagrammile."
    },
    {
      "level": 1,
      "question": "Põhimõiste (Andmebaaside projekteerimine): Üks-mitmele seos. Milline vastus on kõige täpsem?",
      "options": [
        "üks klient, üks andmebaas",
        "üks klient, mitu tellimust",
        "mitu parooli ühes väljas",
        "CSS ja HTML"
      ],
      "correctIndex": 1,
      "explanation": "Üks rida võib olla seotud mitme reaga teises tabelis.",
      "hint": "Mõtle tellimustele."
    },
    {
      "level": 1,
      "question": "Põhimõiste (Andmebaaside projekteerimine): Mitu-mitmele seos. Milline vastus on kõige täpsem?",
      "options": [
        "vajab ühte tekstivälja",
        "keelab primaarvõtme",
        "vajab vahetabelit",
        "asendab SQL-i"
      ],
      "correctIndex": 2,
      "explanation": "Vahetabel hoiab mõlema poole võtmeid.",
      "hint": "Mõtle õpilased ja kursused."
    },
    {
      "level": 1,
      "question": "Põhimõiste (Andmebaaside projekteerimine): Normaliseerimine. Milline vastus on kõige täpsem?",
      "options": [
        "lisab korduvaid välju",
        "eemaldab kõik tabelid",
        "muudab kõik JSON-iks",
        "vähendab dubleerimist"
      ],
      "correctIndex": 3,
      "explanation": "Normaliseerimine aitab andmeid järjepidevalt hoida.",
      "hint": "Mõtle sama info kordamisele."
    },
    {
      "level": 1,
      "question": "Põhimõiste (Dokumentatsiooni koostamine): README eesmärk. Milline vastus on kõige täpsem?",
      "options": [
        "käivitamise ja kasutuse selgitamine",
        "paroolide hoidmine",
        "koodi asendamine",
        "vigade peitmine"
      ],
      "correctIndex": 0,
      "explanation": "README aitab projekti mõista ja käima saada.",
      "hint": "Mõtle uuele arendajale."
    },
    {
      "level": 1,
      "question": "Põhimõiste (Dokumentatsiooni koostamine): API dokumentatsioon. Milline vastus on kõige täpsem?",
      "options": [
        "ainult logo",
        "meetodid, URL-id ja näited",
        "autori paroolid",
        "CSS värvid"
      ],
      "correctIndex": 1,
      "explanation": "API tarbija vajab päringu ja vastuse lepingut.",
      "hint": "Mõtle kliendi arendajale."
    },
    {
      "level": 1,
      "question": "Põhimõiste (Dokumentatsiooni koostamine): Teadaolevad piirangud. Milline vastus on kõige täpsem?",
      "options": [
        "nõrkuse peitmine",
        "testide kustutus",
        "aus ülevaade puudustest",
        "saladuste jagamine"
      ],
      "correctIndex": 2,
      "explanation": "Piirangud aitavad ootusi juhtida ja edasiarendust planeerida.",
      "hint": "Mõtle läbipaistvusele."
    },
    {
      "level": 1,
      "question": "Põhimõiste (Dokumentatsiooni koostamine): Kommentaari parim roll. Milline vastus on kõige täpsem?",
      "options": [
        "korrata ilmset rida",
        "hoida salasõna",
        "asendada test",
        "selgitada miks"
      ],
      "correctIndex": 3,
      "explanation": "Hea kommentaar annab konteksti, mida kood ise ei ütle.",
      "hint": "Mõtle põhjendusele."
    },
    {
      "level": 1,
      "question": "Põhimõiste (JavaScript): `const` kasutus. Milline vastus on kõige täpsem?",
      "options": [
        "väärtust ei määrata ümber",
        "muutuja peab olema globaalne",
        "väärtus on salajane",
        "kood on asünkroonne"
      ],
      "correctIndex": 0,
      "explanation": "const teeb kavatsuse selgemaks ja väldib juhuslikku ümbermääramist.",
      "hint": "Mõtle muutumatule viitele."
    },
    {
      "level": 1,
      "question": "Põhimõiste (JavaScript): Massiivi `map`. Milline vastus on kõige täpsem?",
      "options": [
        "filtreerib ainult",
        "teisendab elemendid uueks massiiviks",
        "muudab HTTP meetodit",
        "loob SQL tabeli"
      ],
      "correctIndex": 1,
      "explanation": "map loob uue massiivi iga elemendi teisenduse põhjal.",
      "hint": "Mõtle üks-ühele teisendusele."
    },
    {
      "level": 1,
      "question": "Põhimõiste (JavaScript): `addEventListener`. Milline vastus on kõige täpsem?",
      "options": [
        "teeb JSON-i",
        "loob andmebaasi",
        "seob sündmuse funktsiooniga",
        "vormindab CSS-i"
      ],
      "correctIndex": 2,
      "explanation": "Sündmusekuulaja võimaldab reageerida kasutaja tegevusele.",
      "hint": "Mõtle klikile."
    },
    {
      "level": 1,
      "question": "Põhimõiste (JavaScript): `fetch`. Milline vastus on kõige täpsem?",
      "options": [
        "leiab DOM elemendi",
        "sorteerib massiivi",
        "kirjutab commit'i",
        "teeb HTTP päringu"
      ],
      "correctIndex": 3,
      "explanation": "fetch küsib andmeid või saadab neid võrgus.",
      "hint": "Mõtle API-ga suhtlemisele."
    },
    {
      "level": 1,
      "question": "Põhimõiste (Märgendikeeled): HTML-i roll. Milline vastus on kõige täpsem?",
      "options": [
        "sisu struktuur",
        "andmebaasi indeks",
        "serveri token",
        "Git ajalugu"
      ],
      "correctIndex": 0,
      "explanation": "HTML annab dokumendile struktuuri ja tähenduse.",
      "hint": "Mõtle lehe skeletile."
    },
    {
      "level": 1,
      "question": "Põhimõiste (Märgendikeeled): Semantiline `nav`. Milline vastus on kõige täpsem?",
      "options": [
        "koodiplokk",
        "navigeerimisala",
        "andmetabel",
        "vormiviga"
      ],
      "correctIndex": 1,
      "explanation": "nav tähistab linkide rühma navigeerimiseks.",
      "hint": "Mõtle menüüle."
    },
    {
      "level": 1,
      "question": "Põhimõiste (Märgendikeeled): `alt` tekst. Milline vastus on kõige täpsem?",
      "options": [
        "käivitab skripti",
        "loob JOINi",
        "kirjeldab pilti",
        "salvestab parooli"
      ],
      "correctIndex": 2,
      "explanation": "Alt tekst aitab kasutajaid, kes pilti ei näe.",
      "hint": "Mõtle ekraanilugejale."
    },
    {
      "level": 1,
      "question": "Põhimõiste (Märgendikeeled): Korrektne pesastamine. Milline vastus on kõige täpsem?",
      "options": [
        "kõik on ühel real",
        "CSS on inline",
        "SQL on uppercase",
        "märgendid sulguvad õiges järjekorras"
      ],
      "correctIndex": 3,
      "explanation": "Õige pesastamine hoiab DOM struktuuri arusaadava.",
      "hint": "Mõtle avamis- ja sulgemismärgenditele."
    },
    {
      "level": 1,
      "question": "Põhimõiste (SQL keele alused): SELECT. Milline vastus on kõige täpsem?",
      "options": [
        "andmete pärimine",
        "tabeli kustutamine",
        "serveri käivitus",
        "CSS import"
      ],
      "correctIndex": 0,
      "explanation": "SELECT loeb andmeid tabelitest.",
      "hint": "Mõtle lugemisele."
    },
    {
      "level": 1,
      "question": "Põhimõiste (SQL keele alused): WHERE. Milline vastus on kõige täpsem?",
      "options": [
        "tabeli ümbernimetamine",
        "ridade filtreerimine",
        "indeksi kustutamine",
        "HTML loomine"
      ],
      "correctIndex": 1,
      "explanation": "WHERE kitsendab tulemust tingimuse järgi.",
      "hint": "Mõtle tingimusele."
    },
    {
      "level": 1,
      "question": "Põhimõiste (SQL keele alused): JOIN. Milline vastus on kõige täpsem?",
      "options": [
        "parooli krüptimine",
        "brauseri laadimine",
        "seotud tabelite ühendamine",
        "CSS värv"
      ],
      "correctIndex": 2,
      "explanation": "JOIN seob tabelid võtmete abil.",
      "hint": "Mõtle kliendile ja tellimusele."
    },
    {
      "level": 1,
      "question": "Põhimõiste (SQL keele alused): ORDER BY. Milline vastus on kõige täpsem?",
      "options": [
        "tabeli kustutamine",
        "API loomine",
        "vormi saatmine",
        "tulemuste sortimine"
      ],
      "correctIndex": 3,
      "explanation": "ORDER BY määrab tulemuste järjekorra.",
      "hint": "Mõtle järjestusele."
    },
    {
      "level": 1,
      "question": "Põhimõiste (Sissejuhatus programmeerimisse): if-lause. Milline vastus on kõige täpsem?",
      "options": [
        "otsuse tegemine",
        "andmebaasi loomine",
        "CSS import",
        "Git merge"
      ],
      "correctIndex": 0,
      "explanation": "if valib tegevuse tingimuse põhjal.",
      "hint": "Mõtle harunemisele."
    },
    {
      "level": 1,
      "question": "Põhimõiste (Sissejuhatus programmeerimisse): Tsükkel. Milline vastus on kõige täpsem?",
      "options": [
        "ainult üks käsk",
        "korduva tegevuse tegemine",
        "serveri sulgemine",
        "parooli hoidmine"
      ],
      "correctIndex": 1,
      "explanation": "Tsükkel töötleb korduvaid samme ilma koodi kopeerimata.",
      "hint": "Mõtle nimekirjale."
    },
    {
      "level": 1,
      "question": "Põhimõiste (Sissejuhatus programmeerimisse): Funktsiooni parameeter. Milline vastus on kõige täpsem?",
      "options": [
        "CSS värv",
        "SQL indeks",
        "sisendi edastamine",
        "HTTP staatus"
      ],
      "correctIndex": 2,
      "explanation": "Parameeter teeb funktsiooni kasutatavaks eri väärtustega.",
      "hint": "Mõtle funktsioonile antavale väärtusele."
    },
    {
      "level": 1,
      "question": "Põhimõiste (Sissejuhatus programmeerimisse): Tagastusväärtus. Milline vastus on kõige täpsem?",
      "options": [
        "HTML atribuut",
        "Git branch",
        "serveri port",
        "funktsiooni tulemus"
      ],
      "correctIndex": 3,
      "explanation": "Return annab arvutatud tulemuse funktsiooni kutsujale.",
      "hint": "Mõtle väljundile."
    },
    {
      "level": 1,
      "question": "Põhimõiste (Testimise alused): Testjuhtum. Milline vastus on kõige täpsem?",
      "options": [
        "sisend, tegevus ja oodatav tulemus",
        "ainult faili nimi",
        "serveri port",
        "CSS klass"
      ],
      "correctIndex": 0,
      "explanation": "Testjuhtum kirjeldab kontrollitavat olukorda.",
      "hint": "Mõtle konkreetsele stsenaariumile."
    },
    {
      "level": 1,
      "question": "Põhimõiste (Testimise alused): Unit test. Milline vastus on kõige täpsem?",
      "options": [
        "kogu kasutajavoo kontroll",
        "väikese koodiosa kontroll",
        "ainult logo vaatamine",
        "deploy"
      ],
      "correctIndex": 1,
      "explanation": "Unit test kontrollib funktsiooni või moodulit eraldi.",
      "hint": "Mõtle väiksele üksusele."
    },
    {
      "level": 1,
      "question": "Põhimõiste (Testimise alused): Regressioon. Milline vastus on kõige täpsem?",
      "options": [
        "uus feature valmis",
        "test läks kiiremaks",
        "varem töötanud asi läks katki",
        "CSS sai ilusam"
      ],
      "correctIndex": 2,
      "explanation": "Regressioon tähendab, et muudatus rikkus olemasoleva käitumise.",
      "hint": "Mõtle tagasi tulnud veale."
    },
    {
      "level": 1,
      "question": "Põhimõiste (Testimise alused): Smoke-test. Milline vastus on kõige täpsem?",
      "options": [
        "täielik turvaaudit",
        "kõigi ridade test",
        "andmebaasi disain",
        "kiire põhivoo kontroll"
      ],
      "correctIndex": 3,
      "explanation": "Smoke-test annab kiire kindluse, et põhiline voog pole katki.",
      "hint": "Mõtle esmastele kontrollidele."
    },
    {
      "level": 1,
      "question": "Põhimõiste (Testimise tüübid ja automatiseerimine): Automatiseerimise mõte. Milline vastus on kõige täpsem?",
      "options": [
        "korduva kontrolli kiirendamine",
        "kõigi käsitsi testide keelamine",
        "vigade peitmine",
        "CSS loomine"
      ],
      "correctIndex": 0,
      "explanation": "Automaatne test kordab sama kontrolli kiiresti ja järjepidevalt.",
      "hint": "Mõtle korduvusele."
    },
    {
      "level": 1,
      "question": "Põhimõiste (Testimise tüübid ja automatiseerimine): Integratsioonitest. Milline vastus on kõige täpsem?",
      "options": [
        "ühe muutuja stiil",
        "mitme osa koos töö kontroll",
        "ainult font",
        "Git alias"
      ],
      "correctIndex": 1,
      "explanation": "Integratsioonitest kontrollib moodulite või teenuste koostööd.",
      "hint": "Mõtle liidestele."
    },
    {
      "level": 1,
      "question": "Põhimõiste (Testimise tüübid ja automatiseerimine): End-to-end test. Milline vastus on kõige täpsem?",
      "options": [
        "ainult funktsiooni sisend",
        "SQL skeem",
        "kasutaja põhivoo kontroll",
        "commit sõnum"
      ],
      "correctIndex": 2,
      "explanation": "E2E test vaatab süsteemi kasutaja teekonnana.",
      "hint": "Mõtle algusest lõpuni voole."
    },
    {
      "level": 1,
      "question": "Põhimõiste (Testimise tüübid ja automatiseerimine): Mock. Milline vastus on kõige täpsem?",
      "options": [
        "parandab productionit",
        "kustutab API",
        "asendab kõik testid",
        "asendab välise sõltuvuse testis"
      ],
      "correctIndex": 3,
      "explanation": "Mock võimaldab kontrollitud vastuseid ilma päris teenuseta.",
      "hint": "Mõtle kontrollitud keskkonnale."
    },
    {
      "level": 1,
      "question": "Põhimõiste (Veebirakenduste loomine klient-server raamistikul): Klient-server mudel. Milline vastus on kõige täpsem?",
      "options": [
        "brauser küsib, server vastab",
        "andmebaas joonistab nupu",
        "CSS teeb päringu",
        "Git renderdab HTML-i"
      ],
      "correctIndex": 0,
      "explanation": "Klient saadab päringu ja server töötleb selle.",
      "hint": "Mõtle brauserile ja serverile."
    },
    {
      "level": 1,
      "question": "Põhimõiste (Veebirakenduste loomine klient-server raamistikul): Endpoint. Milline vastus on kõige täpsem?",
      "options": [
        "CSS klass",
        "serveri konkreetne URL ja loogika",
        "Git branch",
        "HTML pealkiri"
      ],
      "correctIndex": 1,
      "explanation": "Endpoint võtab vastu kindla päringu ja tagastab vastuse.",
      "hint": "Mõtle /api/users tüüpi aadressile."
    },
    {
      "level": 1,
      "question": "Põhimõiste (Veebirakenduste loomine klient-server raamistikul): HTTP request body. Milline vastus on kõige täpsem?",
      "options": [
        "serveri CSS",
        "andmebaasi indeks",
        "päringu andmed",
        "brauseri font"
      ],
      "correctIndex": 2,
      "explanation": "POST või PATCH päring saadab andmeid sageli kehas.",
      "hint": "Mõtle JSON payloadile."
    },
    {
      "level": 1,
      "question": "Põhimõiste (Veebiteenused): REST-is GET. Milline vastus on kõige täpsem?",
      "options": [
        "ressursi kustutamine",
        "parooli räsimine",
        "CSS muutmine",
        "ressursi lugemine"
      ],
      "correctIndex": 3,
      "explanation": "GET küsib andmeid ja ei peaks olekut muutma.",
      "hint": "Mõtle lugemispäringule."
    },
    {
      "level": 1,
      "question": "Põhimõiste (Veebiteenused): REST-is POST. Milline vastus on kõige täpsem?",
      "options": [
        "uue ressursi loomine või käsu saatmine",
        "ainult lugemine",
        "CSS import",
        "Git status"
      ],
      "correctIndex": 0,
      "explanation": "POST saadab serverile andmed töötlemiseks.",
      "hint": "Mõtle vormi saatmisele."
    },
    {
      "level": 1,
      "question": "Põhimõiste (Veebiteenused): HTTP 401. Milline vastus on kõige täpsem?",
      "options": [
        "ressurss loodud",
        "autentimine puudub",
        "ligipääs lubatud",
        "serveri CSS viga"
      ],
      "correctIndex": 1,
      "explanation": "401 tähendab, et kasutaja pole tõendatud.",
      "hint": "Mõtle sisselogimisele."
    },
    {
      "level": 2,
      "question": "Praktiline olukord (Agiilne tarkvaraarendus): Backlogis on liiga suur kasutajalugu. Milline vastus on kõige täpsem?",
      "options": [
        "jaga väiksemateks väärtuslikeks osadeks",
        "võta muutmata sprinti",
        "eemalda vastuvõtutingimused",
        "lükka testid lõppu"
      ],
      "correctIndex": 0,
      "explanation": "Väiksem töö on paremini hinnatav, testitav ja ülevaadatav.",
      "hint": "Mõtle töö viilutamisele."
    },
    {
      "level": 2,
      "question": "Praktiline olukord (Agiilne tarkvaraarendus): Daily muutub pikaks tehniliseks vaidluseks. Milline vastus on kõige täpsem?",
      "options": [
        "pikendada daily lõputult",
        "parkida süvaarutelu eraldi",
        "keelata küsimused",
        "kirjutada kood koosolekul"
      ],
      "correctIndex": 1,
      "explanation": "Daily eesmärk on sünkroonida, mitte lahendada kõiki detaile kõigi ajaga.",
      "hint": "Mõtle koosoleku eesmärgile."
    },
    {
      "level": 2,
      "question": "Praktiline olukord (Agiilne tarkvaraarendus): Acceptance criteria on 'peab olema ilus'. Milline vastus on kõige täpsem?",
      "options": [
        "jäta samaks",
        "asenda commitiga",
        "tee tingimus mõõdetavaks",
        "eemalda issue"
      ],
      "correctIndex": 2,
      "explanation": "Vastuvõtutingimus peab olema konkreetne ja kontrollitav.",
      "hint": "Mõtle testitavusele."
    },
    {
      "level": 2,
      "question": "Praktiline olukord (Agiilne tarkvaraarendus): Sprinti lisatakse pidevalt uusi töid. Milline vastus on kõige täpsem?",
      "options": [
        "töö kiireneb alati",
        "DoD muutub tarbetuks",
        "review pole vaja",
        "fookus ja prognoos kannatavad"
      ],
      "correctIndex": 3,
      "explanation": "Sprint vajab piisavalt stabiilset eesmärki, muidu ei saa tiim lubadust kontrollida.",
      "hint": "Mõtle sprint eesmärgile."
    },
    {
      "level": 2,
      "question": "Praktiline olukord (Agiilse tarkvaraarenduse projekt): PR sisaldab mitut mitteseotud teemat. Milline vastus on kõige täpsem?",
      "options": [
        "jaga väiksemateks PR-ideks",
        "lisa veel faile",
        "keela review",
        "merge'i pimesi"
      ],
      "correctIndex": 0,
      "explanation": "Fookustatud PR-i on lihtsam mõista, testida ja vajadusel tagasi võtta.",
      "hint": "Mõtle review koormusele."
    },
    {
      "level": 2,
      "question": "Praktiline olukord (Agiilse tarkvaraarenduse projekt): Merge conflict samas failis. Milline vastus on kõige täpsem?",
      "options": [
        "jäta konfliktimärgid",
        "lahenda sisuliselt mõlema muudatuse põhjal",
        "kustuta fail",
        "force push maini"
      ],
      "correctIndex": 1,
      "explanation": "Konflikt nõuab arusaamist, milline lõpptulemus peab jääma.",
      "hint": "Mõtle konfliktimärkidele."
    },
    {
      "level": 2,
      "question": "Praktiline olukord (Agiilse tarkvaraarenduse projekt): Issue ja commit pole seotud. Milline vastus on kõige täpsem?",
      "options": [
        "kood töötab kiiremini",
        "DoD paraneb",
        "jälgitavus nõrgeneb",
        "testid kaovad"
      ],
      "correctIndex": 2,
      "explanation": "Issue number või selge viide aitab aru saada, miks muudatus tehti.",
      "hint": "Mõtle arendusprotsessi jäljele."
    },
    {
      "level": 2,
      "question": "Praktiline olukord (Agiilse tarkvaraarenduse projekt): Projektis avastatakse vead alles lõpus. Milline vastus on kõige täpsem?",
      "options": [
        "testi ainult demos",
        "eemalda DoD",
        "suurem sprint",
        "too testid ja review varasemaks"
      ],
      "correctIndex": 3,
      "explanation": "Varane kontroll vähendab hilise parandamise hinda.",
      "hint": "Mõtle feedback loop'ile."
    },
    {
      "level": 2,
      "question": "Praktiline olukord (Andmebaaside alused): Kliendi nimi kordub igal tellimuse real. Milline vastus on kõige täpsem?",
      "options": [
        "tekib dubleerimise risk",
        "JOIN muutub võimatuks",
        "primaarvõti kaob",
        "SQL keelab selle"
      ],
      "correctIndex": 0,
      "explanation": "Korduv info võib muutuda eri ridadel ebaühtlaseks.",
      "hint": "Mõtle uuendusanomaaliale."
    },
    {
      "level": 2,
      "question": "Praktiline olukord (Andmebaaside alused): Kustutatakse klient, kellel on tellimused. Milline vastus on kõige täpsem?",
      "options": [
        "tellimused kaovad alati õigesti",
        "tuleb otsustada viitepiirang",
        "võõrvõti pole oluline",
        "SELECT parandab selle"
      ],
      "correctIndex": 1,
      "explanation": "Foreign key reeglid määravad, kas kustutus keelatakse, kaskaaditakse või käsitletakse teisiti.",
      "hint": "Mõtle seotud ridadele."
    },
    {
      "level": 2,
      "question": "Praktiline olukord (Andmebaaside alused): Kasutaja e-post valitakse primaarvõtmeks. Milline vastus on kõige täpsem?",
      "options": [
        "SQL ei toeta teksti",
        "e-post on alati unikaalne igavesti",
        "see võib ajas muutuda",
        "JOIN muutub kiiremaks"
      ],
      "correctIndex": 2,
      "explanation": "Stabiilsem tehniline id on sageli parem kui muutuv loomulik võti.",
      "hint": "Mõtle võtme stabiilsusele."
    },
    {
      "level": 2,
      "question": "Praktiline olukord (Andmebaaside alused): Indeks lisatakse igale veerule igaks juhuks. Milline vastus on kõige täpsem?",
      "options": [
        "indeksid on tasuta",
        "SELECT läheb alati halvemaks",
        "andmed kustuvad",
        "kirjutamise ja ruumi kulu kasvab"
      ],
      "correctIndex": 3,
      "explanation": "Indeks peab lähtuma päringutest, sest sellel on hooldus- ja ruumikulu.",
      "hint": "Mõtle kompromissile."
    },
    {
      "level": 2,
      "question": "Praktiline olukord (Andmebaaside projekteerimine): Mitut telefoni hoitakse komadega ühes väljas. Milline vastus on kõige täpsem?",
      "options": [
        "pärimine ja valideerimine muutuvad raskeks",
        "see on ideaalne 1NF",
        "JOIN pole enam vaja",
        "primaarvõti paraneb"
      ],
      "correctIndex": 0,
      "explanation": "Mitme väärtuse hoidmine ühes väljas rikub atomaarsete väärtuste põhimõtet.",
      "hint": "Mõtle esimesele normaalvormile."
    },
    {
      "level": 2,
      "question": "Praktiline olukord (Andmebaaside projekteerimine): Tellimuse hind salvestatakse eraldi, kuigi tootel on hind. Milline vastus on kõige täpsem?",
      "options": [
        "see rikub alati mudeli",
        "ajalooline hind peab säilima",
        "hind ei kuulu tellimusele",
        "SQL ei toeta hindu"
      ],
      "correctIndex": 1,
      "explanation": "Tellimus peab kajastama ostuhetke, mitte ainult toote praegust hinda.",
      "hint": "Mõtle ajas muutuvale hinnale."
    },
    {
      "level": 2,
      "question": "Praktiline olukord (Andmebaaside projekteerimine): Atribuut sõltub ainult osast liitvõtmest. Milline vastus on kõige täpsem?",
      "options": [
        "see on alati 3NF",
        "võõrvõti kaob",
        "tekib normaliseerimisprobleem",
        "CSS seos tekib"
      ],
      "correctIndex": 2,
      "explanation": "Osaline sõltuvus põhjustab dubleerimist ja anomaaliaid.",
      "hint": "Mõtle liitvõtmele."
    },
    {
      "level": 2,
      "question": "Praktiline olukord (Andmebaaside projekteerimine): Diagrammis on seos ilma kardinaalsuseta. Milline vastus on kõige täpsem?",
      "options": [
        "see on alati piisav",
        "andmebaas täidab ise",
        "SQL ei vaja seoseid",
        "mudeli tähendus jääb ebaselgeks"
      ],
      "correctIndex": 3,
      "explanation": "Kardinaalsus näitab, mitu kirjet võib kummalgi poolel seotud olla.",
      "hint": "Mõtle üks-mitu-mitu."
    },
    {
      "level": 2,
      "question": "Praktiline olukord (Dokumentatsiooni koostamine): Dokumentatsioonis puuduvad installisammud. Milline vastus on kõige täpsem?",
      "options": [
        "teine arendaja ei saa projekti korrata",
        "see on mugavus",
        "Git lahendab ise",
        "testid pole vajalikud"
      ],
      "correctIndex": 0,
      "explanation": "Käivitusjuhend peab olema piisavalt täpne, et keskkond taastada.",
      "hint": "Mõtle reprodutseeritavusele."
    },
    {
      "level": 2,
      "question": "Praktiline olukord (Dokumentatsiooni koostamine): API dokis puuduvad veavastused. Milline vastus on kõige täpsem?",
      "options": [
        "vead pole API osa",
        "veakäsitlust on raske ehitada",
        "klient arvab ise",
        "HTTP staatus piisab alati"
      ],
      "correctIndex": 1,
      "explanation": "Klient vajab ka vea keha ja staatuste näiteid.",
      "hint": "Mõtle error response'ile."
    },
    {
      "level": 2,
      "question": "Praktiline olukord (Dokumentatsiooni koostamine): Diagramm on ilma tekstilise selgituseta. Milline vastus on kõige täpsem?",
      "options": [
        "diagramm asendab kõik",
        "tekst on alati halb",
        "otsused jäävad tõlgendamiseks",
        "SQL dokumenteerib ise"
      ],
      "correctIndex": 2,
      "explanation": "Tekst selgitab diagrammi tausta, piiranguid ja otsuseid.",
      "hint": "Mõtle lugeja eelteadmistele."
    },
    {
      "level": 2,
      "question": "Praktiline olukord (Dokumentatsiooni koostamine): Dokumentatsioon erineb tegelikust käitumisest. Milline vastus on kõige täpsem?",
      "options": [
        "see pole oluline",
        "kood peab kohanema dokiga",
        "README võib valetada",
        "kasutaja usaldus ja integratsioon kannatavad"
      ],
      "correctIndex": 3,
      "explanation": "Dokumentatsioon on kasulik ainult siis, kui see püsib koodiga kooskõlas.",
      "hint": "Mõtle lepingule."
    },
    {
      "level": 2,
      "question": "Praktiline olukord (JavaScript): `input.value` kasutatakse arvutusel. Milline vastus on kõige täpsem?",
      "options": [
        "teisenda ja kontrolli NaN-i",
        "liida stringid pimesi",
        "kasuta innerHTML-i",
        "tee SQL JOIN"
      ],
      "correctIndex": 0,
      "explanation": "Vormiväärtus on string; arvutuseks on vaja kontrollitud numbrit.",
      "hint": "Mõtle tüübi teisendusele."
    },
    {
      "level": 2,
      "question": "Praktiline olukord (JavaScript): Asünkroonses funktsioonis ununeb `await`. Milline vastus on kõige täpsem?",
      "options": [
        "kood muutub alati kiiremaks",
        "kasutatakse lõpetamata Promise'it",
        "viga kaob",
        "fetch muutub sünkroonseks"
      ],
      "correctIndex": 1,
      "explanation": "Ilma await'ita võib järgnev loogika käivituda enne andmete saabumist.",
      "hint": "Mõtle ajastusele."
    },
    {
      "level": 2,
      "question": "Praktiline olukord (JavaScript): Funktsioon loeb globaalset olekut. Milline vastus on kõige täpsem?",
      "options": [
        "parameetrid on keelatud",
        "DOM muutub kiiremaks",
        "testitavus halveneb",
        "SQL paraneb"
      ],
      "correctIndex": 2,
      "explanation": "Selged sisendid parameetritena teevad funktsiooni ennustatavamaks.",
      "hint": "Mõtle nähtavatele sõltuvustele."
    },
    {
      "level": 2,
      "question": "Praktiline olukord (JavaScript): Vana API vastus saabub pärast uut. Milline vastus on kõige täpsem?",
      "options": [
        "kuva mõlemad pimesi",
        "lisa CSS vari",
        "tee force push",
        "kontrolli päringu id-d või katkesta vana"
      ],
      "correctIndex": 3,
      "explanation": "Võidujooksu vältimiseks peab UI teadma, milline vastus on uusim.",
      "hint": "Mõtle race condition'ile."
    },
    {
      "level": 2,
      "question": "Praktiline olukord (Märgendikeeled): Leht koosneb ainult `div` elementidest. Milline vastus on kõige täpsem?",
      "options": [
        "semantiline tähendus väheneb",
        "div on alati keelatud",
        "CSS ei tööta",
        "API ei loe HTML-i"
      ],
      "correctIndex": 0,
      "explanation": "Semantilised elemendid aitavad nii arendajat kui abitehnoloogiat.",
      "hint": "Mõtle header, main ja nav peale."
    },
    {
      "level": 2,
      "question": "Praktiline olukord (Märgendikeeled): Ikooniga nupul pole teksti. Milline vastus on kõige täpsem?",
      "options": [
        "suurenda z-indexit",
        "lisa ligipääsetav nimi",
        "tee nupp väiksemaks",
        "asenda SQL-iga"
      ],
      "correctIndex": 1,
      "explanation": "Nupul peab olema nimi, mida ekraanilugeja saab ette lugeda.",
      "hint": "Mõtle aria-labelile või nähtavale tekstile."
    },
    {
      "level": 2,
      "question": "Praktiline olukord (Märgendikeeled): Vormivead on ainult punased raamid. Milline vastus on kõige täpsem?",
      "options": [
        "värv piisab alati",
        "peida vead",
        "lisa tekstiline selgitus",
        "kasuta ainult hoverit"
      ],
      "correctIndex": 2,
      "explanation": "Ainult värv ei pruugi olla kõigile tajutav ega piisavalt selge.",
      "hint": "Mõtle ligipääsetavusele."
    },
    {
      "level": 2,
      "question": "Praktiline olukord (Märgendikeeled): Tabelit kasutatakse paigutuseks. Milline vastus on kõige täpsem?",
      "options": [
        "tabel on alati keelatud",
        "SQL tabel nõuab seda",
        "CSS ei oska paigutada",
        "semantika on vale"
      ],
      "correctIndex": 3,
      "explanation": "Tabel sobib tabelandmetele; paigutuseks kasutatakse CSS-i.",
      "hint": "Mõtle sisu tähendusele."
    },
    {
      "level": 2,
      "question": "Praktiline olukord (SQL keele alused): Kõiki kliente on vaja näha ka tellimusteta. Milline vastus on kõige täpsem?",
      "options": [
        "kasuta LEFT JOINi",
        "INNER JOIN alati",
        "DELETE JOIN",
        "CROSS JOIN pimesi"
      ],
      "correctIndex": 0,
      "explanation": "LEFT JOIN säilitab vasaku tabeli read ka siis, kui seost pole.",
      "hint": "Mõtle puuduvale seosele."
    },
    {
      "level": 2,
      "question": "Praktiline olukord (SQL keele alused): Tellimuste arv kliendi kaupa. Milline vastus on kõige täpsem?",
      "options": [
        "DELETE ja DROP",
        "GROUP BY ja COUNT",
        "ORDER BY ainult",
        "INSERT ja UPDATE"
      ],
      "correctIndex": 1,
      "explanation": "Koondamiseks rühmade kaupa kasutatakse GROUP BY-d ja agregaatfunktsioone.",
      "hint": "Mõtle loendamisele."
    },
    {
      "level": 2,
      "question": "Praktiline olukord (SQL keele alused): Tingimus `name='Mari' OR 'Jaan'`. Milline vastus on kõige täpsem?",
      "options": [
        "see on korrektne",
        "OR keelab teksti",
        "teine pool pole võrdlus",
        "WHERE peab tühi olema"
      ],
      "correctIndex": 2,
      "explanation": "Mõlemal OR poolel peab olema loogiline tingimus või tuleb kasutada IN.",
      "hint": "Mõtle, mida võrreldakse."
    },
    {
      "level": 2,
      "question": "Praktiline olukord (SQL keele alused): SELECT * tootmiskoodis. Milline vastus on kõige täpsem?",
      "options": [
        "see on alati parim",
        "WHERE ei tööta muidu",
        "JOIN vajab seda",
        "liigsed väljad liiguvad kaasa"
      ],
      "correctIndex": 3,
      "explanation": "Vajalike veergude nimetamine vähendab andmemahtu ja sõltuvust tabeli muutustest.",
      "hint": "Mõtle minimaalsele andmehulgale."
    },
    {
      "level": 2,
      "question": "Praktiline olukord (Sissejuhatus programmeerimisse): Funktsioon tagastab vahel numbri ja vahel teksti 'viga'. Milline vastus on kõige täpsem?",
      "options": [
        "leping on ebajärjekindel",
        "see on alati mugav",
        "CSS parandab",
        "SQL nõuab seda"
      ],
      "correctIndex": 0,
      "explanation": "Eri tüüpi tagastused muudavad kasutava koodi keerulisemaks.",
      "hint": "Mõtle funktsiooni lepingule."
    },
    {
      "level": 2,
      "question": "Praktiline olukord (Sissejuhatus programmeerimisse): Massiivi muudetakse samal ajal, kui seda indeksiga läbitakse. Milline vastus on kõige täpsem?",
      "options": [
        "see on alati ohutu",
        "osa elemente võib vahele jääda",
        "DOM parandab",
        "Git taastab"
      ],
      "correctIndex": 1,
      "explanation": "Eemaldamine muudab indeksite asukohta ja võib tsükli tulemust rikkuda.",
      "hint": "Mõtle indeksite nihkumisele."
    },
    {
      "level": 2,
      "question": "Praktiline olukord (Sissejuhatus programmeerimisse): Keeruline tingimus on ühes pikas if-lauses. Milline vastus on kõige täpsem?",
      "options": [
        "asenda kõik true-ga",
        "eemalda tingimus",
        "nimeta vahetingimused",
        "pane CSS-i"
      ],
      "correctIndex": 2,
      "explanation": "Selged vaheväärtused aitavad ärireeglit lugeda ja testida.",
      "hint": "Mõtle loetavusele."
    },
    {
      "level": 2,
      "question": "Praktiline olukord (Sissejuhatus programmeerimisse): Arvutusloogika on segatud DOM-i muutmisega. Milline vastus on kõige täpsem?",
      "options": [
        "DOM on alati halb",
        "testid pole vaja",
        "HTML teeb arvutuse",
        "eralda puhas funktsioon"
      ],
      "correctIndex": 3,
      "explanation": "Eraldi arvutusfunktsiooni saab unit testida ilma brauserita.",
      "hint": "Mõtle testitavusele."
    },
    {
      "level": 2,
      "question": "Praktiline olukord (Testimise alused): Test katab ainult õnneliku tee. Milline vastus on kõige täpsem?",
      "options": [
        "vea- ja piirjuhtumid jäävad katmata",
        "see on alati piisav",
        "vigane sisend pole oluline",
        "testid muutuvad halvemaks"
      ],
      "correctIndex": 0,
      "explanation": "Hea testikomplekt sisaldab ka tühja sisendit, vigu ja piire.",
      "hint": "Mõtle negatiivsetele juhtudele."
    },
    {
      "level": 2,
      "question": "Praktiline olukord (Testimise alused): Unit test kasutab päris andmebaasi ja jätab andmeid. Milline vastus on kõige täpsem?",
      "options": [
        "see on isoleeritud",
        "testid mõjutavad üksteist",
        "andmed puhastuvad ise",
        "CSS lahendab"
      ],
      "correctIndex": 1,
      "explanation": "Test peab olema korduvkäivitatav ja sõltumatu.",
      "hint": "Mõtle testide isoleerimisele."
    },
    {
      "level": 2,
      "question": "Praktiline olukord (Testimise alused): Test kontrollib ainult elemendi olemasolu. Milline vastus on kõige täpsem?",
      "options": [
        "olemasolu tõestab kõik",
        "nuppe ei pea klikkima",
        "käitumine võib jääda katmata",
        "tekst pole oluline"
      ],
      "correctIndex": 2,
      "explanation": "Oluline on kontrollida kasutajale nähtavat tulemust ja tegevust.",
      "hint": "Mõtle käitumisele."
    },
    {
      "level": 2,
      "question": "Praktiline olukord (Testimise alused): Manuaalne testimine enne release'i. Milline vastus on kõige täpsem?",
      "options": [
        "piisab mälust",
        "testid pole korratavad",
        "tulemust ei dokumenteerita",
        "vajab kirjalikku kontrollnimekirja"
      ],
      "correctIndex": 3,
      "explanation": "Kirjalik checklist teeb käsitsi kontrolli korratavaks ja tõendatavaks.",
      "hint": "Mõtle reprodutseeritavusele."
    },
    {
      "level": 2,
      "question": "Praktiline olukord (Testimise tüübid ja automatiseerimine): UI test ootab fikseeritud 5 sekundit. Milline vastus on kõige täpsem?",
      "options": [
        "oota konkreetset olekut",
        "suurenda paus minutiks",
        "eemalda kontroll",
        "käivita käsitsi"
      ],
      "correctIndex": 0,
      "explanation": "Olekupõhine ootamine on stabiilsem kui sleep.",
      "hint": "Mõtle, mida kasutaja näeb."
    },
    {
      "level": 2,
      "question": "Praktiline olukord (Testimise tüübid ja automatiseerimine): Automaatne test jätab loodud andmed alles. Milline vastus on kõige täpsem?",
      "options": [
        "see on hea cache",
        "järgmine käivitus võib ebaõnnestuda",
        "andmeid ei pea puhastama",
        "testid on alati sõltumatud"
      ],
      "correctIndex": 1,
      "explanation": "Test peab looma ja koristama oma andmed või kasutama isoleeritud keskkonda.",
      "hint": "Mõtle korduskäivitatavusele."
    },
    {
      "level": 2,
      "question": "Praktiline olukord (Testimise tüübid ja automatiseerimine): Test kontrollib privaatset klassinime. Milline vastus on kõige täpsem?",
      "options": [
        "see on parim leping",
        "kasutaja näeb klassi",
        "refaktor võib testi asjata lõhkuda",
        "CSS on API"
      ],
      "correctIndex": 2,
      "explanation": "Eelistada tuleks nähtavat käitumist ja avalikku lepingut.",
      "hint": "Mõtle implementation detail'ile."
    },
    {
      "level": 2,
      "question": "Praktiline olukord (Testimise tüübid ja automatiseerimine): CI käivitab testid iga pushiga. Milline vastus on kõige täpsem?",
      "options": [
        "testid käivad ainult release'il",
        "CI asendab review",
        "CI peidab vigu",
        "vead leitakse varem"
      ],
      "correctIndex": 3,
      "explanation": "Pidev kontroll vähendab hilise avastamise hinda.",
      "hint": "Mõtle varasele tagasisidele."
    },
    {
      "level": 2,
      "question": "Praktiline olukord (Veebirakenduste loomine klient-server raamistikul): Frontend valideerib, aga server mitte. Milline vastus on kõige täpsem?",
      "options": [
        "reeglist saab mööda hiilida",
        "frontend on alati usaldusväärne",
        "CSS kaitseb",
        "GET parandab"
      ],
      "correctIndex": 0,
      "explanation": "Kasutaja saab klienti muuta või saata päringu otse serverile.",
      "hint": "Mõtle usalduspiirile."
    },
    {
      "level": 2,
      "question": "Praktiline olukord (Veebirakenduste loomine klient-server raamistikul): Klient saadab JSON-i vale Content-Type'iga. Milline vastus on kõige täpsem?",
      "options": [
        "JSON parandab päise ise",
        "server ei pruugi keha parsida",
        "CSS loeb keha",
        "SQL määrab tüübi"
      ],
      "correctIndex": 1,
      "explanation": "Päis ja serveri parser peavad kokku sobima.",
      "hint": "Mõtle andmevahetuse lepingule."
    },
    {
      "level": 2,
      "question": "Praktiline olukord (Veebirakenduste loomine klient-server raamistikul): Topeltklõps saadab vormi kaks korda. Milline vastus on kõige täpsem?",
      "options": [
        "peida nupp igaveseks",
        "ignoreeri probleemi",
        "vaja on kliendi ja/või serveri kaitset",
        "tee päring GETiks"
      ],
      "correctIndex": 2,
      "explanation": "Nupu keelamine ja serveripoolne duplikaadikontroll võivad mõlemad vajalikud olla.",
      "hint": "Mõtle idempotentsusele."
    },
    {
      "level": 2,
      "question": "Praktiline olukord (Veebiteenused): PUT ja PATCH erinevus. Milline vastus on kõige täpsem?",
      "options": [
        "PATCH ainult loeb",
        "PUT kustutab alati",
        "mõlemad on CSS",
        "PATCH muudab osa ressursist"
      ],
      "correctIndex": 3,
      "explanation": "PUT seostub sageli terviku asendamisega, PATCH osalise muutmisega.",
      "hint": "Mõtle osalisele uuendusele."
    },
    {
      "level": 2,
      "question": "Praktiline olukord (Veebiteenused): API tagastab palju andmeid korraga. Milline vastus on kõige täpsem?",
      "options": [
        "kasuta paginationit või piirangut",
        "saada alati kõik",
        "keela GET",
        "tee JSON pildiks"
      ],
      "correctIndex": 0,
      "explanation": "Andmemahu kasvades muutub piiramine jõudluse ja kasutatavuse jaoks oluliseks.",
      "hint": "Mõtle suurele nimekirjale."
    },
    {
      "level": 2,
      "question": "Praktiline olukord (Veebiteenused): Veateate keha pole standardne. Milline vastus on kõige täpsem?",
      "options": [
        "see on paindlik alati",
        "klient peab iga viga eraldi arvama",
        "staatusest piisab alati",
        "JSON keelab vead"
      ],
      "correctIndex": 1,
      "explanation": "Ühtne veavorm lihtsustab klientide veakäsitlust.",
      "hint": "Mõtle API tarbijale."
    },
    {
      "level": 3,
      "question": "Analüüsiolukord (Agiilne tarkvaraarendus): Velocity on tiimi ainus edukuse mõõdik. Milline vastus on kõige täpsem?",
      "options": [
        "väärtus ja kvaliteet jäävad varju",
        "velocity mõõdab kasutajaväärtust",
        "testid pole vajalikud",
        "story point on raha"
      ],
      "correctIndex": 0,
      "explanation": "Kiirus on planeerimise abivahend, mitte eesmärk. Valmis väärtus ja kvaliteet on tähtsamad.",
      "hint": "Mõtle, mida kasutaja päriselt saab."
    },
    {
      "level": 3,
      "question": "Analüüsiolukord (Agiilne tarkvaraarendus): Scope suureneb, kuid tähtaeg ja kvaliteedinõue jäävad samaks. Milline vastus on kõige täpsem?",
      "options": [
        "eemalda testid",
        "räägi läbi mõju ja prioriteedid",
        "nõustu vaikides",
        "peida risk"
      ],
      "correctIndex": 1,
      "explanation": "Agiilsus tähendab muutustega kohanemist, mitte nähtamatu töö lisamist ilma kompromissita.",
      "hint": "Mõtle aja, mahu ja kvaliteedi seosele."
    },
    {
      "level": 3,
      "question": "Analüüsiolukord (Agiilne tarkvaraarendus): Retrospektiiv lõpeb lausega 'teeme paremini'. Milline vastus on kõige täpsem?",
      "options": [
        "see on piisav DoD",
        "see asendab plaani",
        "puudub konkreetne parendustegevus",
        "see sulgeb riskid"
      ],
      "correctIndex": 2,
      "explanation": "Retrospektiiv peab andma katsetatava tegevuse, mille mõju saab hiljem hinnata.",
      "hint": "Mõtle järgmise sprindi kokkuleppele."
    },
    {
      "level": 3,
      "question": "Analüüsiolukord (Agiilne tarkvaraarendus): Tehniline võlg pole kasutajale nähtav. Milline vastus on kõige täpsem?",
      "options": [
        "peida backlogist",
        "keela feature'id",
        "ignoreeri kuni lõpuni",
        "seosta see riski ja tulevase kiirusega"
      ],
      "correctIndex": 3,
      "explanation": "Tehniline võlg mõjutab vigade riski, muudatuste hinda ja arenduskiirust.",
      "hint": "Mõtle pikaajalisele hinnale."
    },
    {
      "level": 3,
      "question": "Analüüsiolukord (Agiilse tarkvaraarenduse projekt): Suur funktsioon valmis ühe hiigelcommitina. Milline vastus on kõige täpsem?",
      "options": [
        "risk ja review raskus kasvavad",
        "see on alati parim",
        "Git nõuab seda",
        "testid muutuvad lihtsamaks"
      ],
      "correctIndex": 0,
      "explanation": "Väikesed loogilised commit'id lihtsustavad ajalugu, review'd ja vea leidmist.",
      "hint": "Mõtle muudatuse granulaarsusele."
    },
    {
      "level": 3,
      "question": "Analüüsiolukord (Agiilse tarkvaraarenduse projekt): Demo näitab ainult koodi, mitte kasutajavoogu. Milline vastus on kõige täpsem?",
      "options": [
        "koodivaade asendab UX-i",
        "väärtus jääb tõestamata",
        "kasutajat pole vaja",
        "testid piisavad alati"
      ],
      "correctIndex": 1,
      "explanation": "Projektidemo peab näitama, et lahendus täidab kasutaja vajaduse.",
      "hint": "Mõtle kasutaja teekonnale."
    },
    {
      "level": 3,
      "question": "Analüüsiolukord (Agiilse tarkvaraarenduse projekt): Review kommentaarid käsitletakse isikliku kriitikana. Milline vastus on kõige täpsem?",
      "options": [
        "review on süüdistus",
        "kommentaarid tuleb peita",
        "tiimi õppimine kannatab",
        "testid pole tähtsad"
      ],
      "correctIndex": 2,
      "explanation": "Review eesmärk on kvaliteet ja ühine arusaam, mitte süüdlase otsimine.",
      "hint": "Mõtle koostööle."
    },
    {
      "level": 3,
      "question": "Analüüsiolukord (Agiilse tarkvaraarenduse projekt): Uus töö alustatakse ilma issue ja vastuvõtutingimusteta. Milline vastus on kõige täpsem?",
      "options": [
        "see kiirendab alati",
        "README asendab kõike",
        "branch pole vajalik",
        "pole selget probleemi ega valmiduse mõõtu"
      ],
      "correctIndex": 3,
      "explanation": "Issue hoiab töö eesmärgi, ulatuse ja kontrolli läbipaistvana.",
      "hint": "Mõtle 'miks' ja 'millal valmis'."
    },
    {
      "level": 3,
      "question": "Analüüsiolukord (Andmebaaside alused): Transaktsioonita rahaülekanne katkeb poole peal. Milline vastus on kõige täpsem?",
      "options": [
        "andmed jäävad vastuoluliseks",
        "see on ainult UI probleem",
        "SELECT parandab selle",
        "CSS rollbackib"
      ],
      "correctIndex": 0,
      "explanation": "Seotud muudatused peavad õnnestuma koos või tagasi pöörduma.",
      "hint": "Mõtle atomaarsele tegevusele."
    },
    {
      "level": 3,
      "question": "Analüüsiolukord (Andmebaaside alused): Parool salvestatakse andmebaasi plain text kujul. Milline vastus on kõige täpsem?",
      "options": [
        "UI peitmine piisab",
        "leke paljastab paroolid",
        "väli tuleb ümber nimetada",
        "SQL indeks kaitseb"
      ],
      "correctIndex": 1,
      "explanation": "Paroole tuleb salvestada tugeva soolatud räsina, mitte loetava tekstina.",
      "hint": "Mõtle andmeleket."
    },
    {
      "level": 3,
      "question": "Analüüsiolukord (Andmebaaside alused): Migratsioon teeb veeru NOT NULL, kuid vanad read sisaldavad NULL-e. Milline vastus on kõige täpsem?",
      "options": [
        "andmed täituvad ise",
        "CSS lahendab",
        "migratsioon võib ebaõnnestuda",
        "testid pole vajalikud"
      ],
      "correctIndex": 2,
      "explanation": "Enne piirangu lisamist tuleb olemasolevad andmed korrastada või vaikimisi väärtus määrata.",
      "hint": "Mõtle olemasolevale andmeseisule."
    },
    {
      "level": 3,
      "question": "Analüüsiolukord (Andmebaaside alused): Aeglase päringu parandamiseks lisatakse juhuslik indeks. Milline vastus on kõige täpsem?",
      "options": [
        "juhuslik indeks on alati parim",
        "WHERE tuleb eemaldada",
        "JOIN keelata",
        "diagnoosita võib probleem jääda"
      ],
      "correctIndex": 3,
      "explanation": "Kõigepealt tuleb vaadata päringu plaani ja tegelikku kitsaskohta.",
      "hint": "Mõtle mõõtmisele enne parandamist."
    },
    {
      "level": 3,
      "question": "Analüüsiolukord (Andmebaaside projekteerimine): Täielik normaliseerimine teeb raportid väga aeglaseks. Milline vastus on kõige täpsem?",
      "options": [
        "kaalu dokumenteeritud denormaliseerimist",
        "ignoreeri jõudlust",
        "eemalda seosed",
        "tee kõik tekstiks"
      ],
      "correctIndex": 0,
      "explanation": "Mudel võib vajada põhjendatud kompromissi, kui kasutusjuht seda nõuab.",
      "hint": "Mõtle teadlikule erandile."
    },
    {
      "level": 3,
      "question": "Analüüsiolukord (Andmebaaside projekteerimine): Kaskaadkustutus eemaldab äriliselt olulise ajaloo. Milline vastus on kõige täpsem?",
      "options": [
        "CASCADE sobib alati",
        "domeeni reegel on valesti valitud",
        "ajalugu pole andmetes tähtis",
        "SELECT taastab read"
      ],
      "correctIndex": 1,
      "explanation": "Kustutusreegel peab vastama andmete elutsüklile ja õiguslikele vajadustele.",
      "hint": "Mõtle andmete säilitamisele."
    },
    {
      "level": 3,
      "question": "Analüüsiolukord (Andmebaaside projekteerimine): Sama olem on modelleeritud kahes kohas eri nimedega. Milline vastus on kõige täpsem?",
      "options": [
        "see parandab paindlikkust",
        "see on alati vajalik",
        "tõlgendused ja andmed lahknevad",
        "JOIN muutub lihtsamaks"
      ],
      "correctIndex": 2,
      "explanation": "Üks mõiste peaks olema mudelis üheselt defineeritud.",
      "hint": "Mõtle ühtsele sõnavarale."
    },
    {
      "level": 3,
      "question": "Analüüsiolukord (Andmebaaside projekteerimine): Mudelit tehakse otse tabelitena ilma nõuete analüüsita. Milline vastus on kõige täpsem?",
      "options": [
        "see on alati kiirem lõpus",
        "ERD pole kunagi vajalik",
        "testid asendavad mudeli",
        "olulised seosed võivad puudu jääda"
      ],
      "correctIndex": 3,
      "explanation": "Andmemudel peaks lähtuma domeeni reeglitest ja kasutusjuhtudest.",
      "hint": "Mõtle enne ehitamist kavandamisele."
    },
    {
      "level": 3,
      "question": "Analüüsiolukord (Dokumentatsiooni koostamine): Arhitektuuriotsust ei dokumenteerita. Milline vastus on kõige täpsem?",
      "options": [
        "otsuse põhjus kaob",
        "kõik mäletavad alati",
        "Git diff on piisav",
        "testid selgitavad äripõhjust"
      ],
      "correctIndex": 0,
      "explanation": "Hiljem on oluline teada, miks valiti just see lahendus ja millised alternatiivid tagasi lükati.",
      "hint": "Mõtle ADR-ile."
    },
    {
      "level": 3,
      "question": "Analüüsiolukord (Dokumentatsiooni koostamine): Dokumentatsioon sisaldab production saladusi. Milline vastus on kõige täpsem?",
      "options": [
        "see aitab käivitada",
        "saladused lekivad",
        "README krüpteerib",
        "Git peidab need"
      ],
      "correctIndex": 1,
      "explanation": "Dokumentatsioon ei tohi sisaldada paroole ega API võtmeid.",
      "hint": "Mõtle turvalisusele."
    },
    {
      "level": 3,
      "question": "Analüüsiolukord (Dokumentatsiooni koostamine): Testimisplaan loetleb ainult tööriistad. Milline vastus on kõige täpsem?",
      "options": [
        "tööriistad on piisav plaan",
        "testandmeid pole vaja",
        "riskid ja stsenaariumid puuduvad",
        "oodatav tulemus pole tähtis"
      ],
      "correctIndex": 2,
      "explanation": "Plaan peab kirjeldama, mida, miks ja milliste andmetega kontrollitakse.",
      "hint": "Mõtle testimise eesmärgile."
    },
    {
      "level": 3,
      "question": "Analüüsiolukord (Dokumentatsiooni koostamine): Dokumentatsiooni uuendatakse alles projekti lõpus. Milline vastus on kõige täpsem?",
      "options": [
        "mälu on alati täpne",
        "lõpus on lihtsam kõike teada",
        "kood ei muutu",
        "info võib olla ebatäpne ja puudulik"
      ],
      "correctIndex": 3,
      "explanation": "Dokumentatsioon peaks arenema koos lahendusega, eriti otsuste ja piirangute osas.",
      "hint": "Mõtle iteratiivsele tööle."
    },
    {
      "level": 3,
      "question": "Analüüsiolukord (JavaScript): Moodul teeb importimisel kohe API päringu. Milline vastus on kõige täpsem?",
      "options": [
        "tekib varjatud kõrvalmõju",
        "import on alati õige koht",
        "testid muutuvad lihtsamaks",
        "Promise kaob"
      ],
      "correctIndex": 0,
      "explanation": "Peidetud kõrvalmõju teeb mooduli testimise ja kasutamise raskemaks.",
      "hint": "Mõtle importimise käitumisele."
    },
    {
      "level": 3,
      "question": "Analüüsiolukord (JavaScript): Globaalne state hoiab mitme mängu andmeid. Milline vastus on kõige täpsem?",
      "options": [
        "globaalne state on alati turvaline",
        "sessioonid võivad seguneda",
        "CSS eraldab kasutajad",
        "JSON lahendab ise"
      ],
      "correctIndex": 1,
      "explanation": "Jagatud olek võib eri kasutajate või mängude andmeid üle kirjutada.",
      "hint": "Mõtle isoleeritud sessioonile."
    },
    {
      "level": 3,
      "question": "Analüüsiolukord (JavaScript): Viga püütakse kinni ja asendatakse üldise veaga ilma põhjuseta. Milline vastus on kõige täpsem?",
      "options": [
        "see parandab vea",
        "kasutaja vajab stack trace'i",
        "diagnoosimise kontekst kaob",
        "logisid pole vaja"
      ],
      "correctIndex": 2,
      "explanation": "UI võib olla üldine, kuid logides peab säilima tehniline põhjus.",
      "hint": "Mõtle kahte sihtrühma."
    },
    {
      "level": 3,
      "question": "Analüüsiolukord (JavaScript): Tsüklis tehakse igale elemendile järjest API päring. Milline vastus on kõige täpsem?",
      "options": [
        "järjestikune on alati parim",
        "API peab ootama",
        "CSS kiirendab",
        "võib tekkida jõudlusprobleem"
      ],
      "correctIndex": 3,
      "explanation": "Palju järjestikuseid päringuid võib asendada koondpäringu või piiratud paralleelsusega.",
      "hint": "Mõtle N+1 mustrile."
    },
    {
      "level": 3,
      "question": "Analüüsiolukord (Märgendikeeled): Brauser parandab vigase HTML-i ise. Milline vastus on kõige täpsem?",
      "options": [
        "DOM võib tulla ootamatu",
        "sellele võib alati loota",
        "CSS ei sõltu DOM-ist",
        "valideerimine pole vajalik"
      ],
      "correctIndex": 0,
      "explanation": "Automaatparandus võib luua teise struktuuri kui arendaja eeldab.",
      "hint": "Mõtle tegelikule DOM-puule."
    },
    {
      "level": 3,
      "question": "Analüüsiolukord (Märgendikeeled): Kõigile elementidele lisatakse aria-label. Milline vastus on kõige täpsem?",
      "options": [
        "ARIA asendab semantika alati",
        "liigne ARIA võib segada",
        "HTML elemente pole vaja",
        "ekraanilugeja ignoreerib kõike"
      ],
      "correctIndex": 1,
      "explanation": "Eelistada tuleb semantilist HTML-i ja lisada ARIA ainult vajadusel.",
      "hint": "Mõtle native first põhimõttele."
    },
    {
      "level": 3,
      "question": "Analüüsiolukord (Märgendikeeled): Kuupäev saadetakse eri lokaalides tekstina. Milline vastus on kõige täpsem?",
      "options": [
        "jäta server arvama",
        "saada pildina",
        "kasuta ühtset ISO formaati",
        "kasuta kuu nime"
      ],
      "correctIndex": 2,
      "explanation": "Ühtne andmevorming vähendab kliendi ja serveri vahelisi parsimisvigu.",
      "hint": "Mõtle andmelepingule."
    },
    {
      "level": 3,
      "question": "Analüüsiolukord (Märgendikeeled): HTML id kordub mitmel elemendil. Milline vastus on kõige täpsem?",
      "options": [
        "id peabki korduma",
        "CSS nõuab kordust",
        "brauser keelab kõik",
        "DOM valik ja ligipääsetavus võivad katki minna"
      ],
      "correctIndex": 3,
      "explanation": "id on mõeldud ühe elemendi unikaalseks tuvastamiseks.",
      "hint": "Mõtle unikaalsusele."
    },
    {
      "level": 3,
      "question": "Analüüsiolukord (SQL keele alused): Sisend liidetakse otse SQL stringi. Milline vastus on kõige täpsem?",
      "options": [
        "SQL injection risk",
        "normaliseerimise risk",
        "CORS risk",
        "CSS risk"
      ],
      "correctIndex": 0,
      "explanation": "Parameetriseeritud päring käsitleb sisendit andmetena, mitte SQL süntaksina.",
      "hint": "Mõtle pahatahtlikule sisendile."
    },
    {
      "level": 3,
      "question": "Analüüsiolukord (SQL keele alused): Päring viie JOINiga on aeglane. Milline vastus on kõige täpsem?",
      "options": [
        "lisa juhuslik indeks",
        "uuri query plaani",
        "eemalda kõik WHERE-id",
        "asenda SQL CSS-iga"
      ],
      "correctIndex": 1,
      "explanation": "Query plan näitab tegelikku täitmist ja aitab valida õige optimeeringu.",
      "hint": "Mõtle mõõtmisele."
    },
    {
      "level": 3,
      "question": "Analüüsiolukord (SQL keele alused): Raportist kaovad seoseta read. Milline vastus on kõige täpsem?",
      "options": [
        "SQL kustutab read",
        "ORDER BY peidab need",
        "JOIN tüüp võib olla vale",
        "COUNT keelab need"
      ],
      "correctIndex": 2,
      "explanation": "INNER JOIN eemaldab read, millel pole vastet. Vajadusel kasuta OUTER JOINi.",
      "hint": "Mõtle seoseta andmetele."
    },
    {
      "level": 3,
      "question": "Analüüsiolukord (SQL keele alused): Indeks igale veerule. Milline vastus on kõige täpsem?",
      "options": [
        "indeksid on tasuta",
        "andmed normaliseeruvad",
        "SELECT ei tööta",
        "kirjutamine ja hooldus kallinevad"
      ],
      "correctIndex": 3,
      "explanation": "Indeksid aitavad lugemist, kuid lisavad kirjutamise ja ruumi kulu.",
      "hint": "Mõtle kompromissile."
    },
    {
      "level": 3,
      "question": "Analüüsiolukord (Sissejuhatus programmeerimisse): Rekursioonil puudub baasjuht. Milline vastus on kõige täpsem?",
      "options": [
        "tekib lõputu rekursioon",
        "funktsioon muutub kiiremaks",
        "SQL parandab selle",
        "CSS peatab"
      ],
      "correctIndex": 0,
      "explanation": "Baasjuht lõpetab rekursiivsed väljakutsed.",
      "hint": "Mõtle lõpetamistingimusele."
    },
    {
      "level": 3,
      "question": "Analüüsiolukord (Sissejuhatus programmeerimisse): Algoritm töötab 10 elemendiga, kuid mitte 10000 elemendiga. Milline vastus on kõige täpsem?",
      "options": [
        "väikesed testid tõestavad kõik",
        "keerukus võib olla halb",
        "andmed peavad olema väikesed",
        "UI lahendab"
      ],
      "correctIndex": 1,
      "explanation": "Sisendi kasv võib paljastada ebaefektiivse algoritmi.",
      "hint": "Mõtle andmemahu kasvule."
    },
    {
      "level": 3,
      "question": "Analüüsiolukord (Sissejuhatus programmeerimisse): Funktsioon muudab sisendmassiivi ootamatult. Milline vastus on kõige täpsem?",
      "options": [
        "mutatsioon on alati soovitud",
        "return pole vajalik",
        "kõrvalmõju võib kutsujat rikkuda",
        "testid ei märka"
      ],
      "correctIndex": 2,
      "explanation": "Kui funktsioon muudab sisendit, peab see olema teadlik ja dokumenteeritud valik.",
      "hint": "Mõtle kõrvalmõjule."
    },
    {
      "level": 3,
      "question": "Analüüsiolukord (Sissejuhatus programmeerimisse): Viga püütakse kinni, kuid programm jätkab vigase olekuga. Milline vastus on kõige täpsem?",
      "options": [
        "catch parandab kõik",
        "vead tuleb ignoreerida",
        "UI varjab alati",
        "hilisem tulemus võib olla vale"
      ],
      "correctIndex": 3,
      "explanation": "Pärast kriitilist viga tuleb olek taastada, katkestada või kasutajale selgelt teada anda.",
      "hint": "Mõtle vigasele olekule."
    },
    {
      "level": 3,
      "question": "Analüüsiolukord (Testimise alused): Flaky test parandatakse assertioni eemaldamisega. Milline vastus on kõige täpsem?",
      "options": [
        "test kaotab väärtuse",
        "see on õige parandus",
        "viga kaob tootest",
        "test muutub täpsemaks"
      ],
      "correctIndex": 0,
      "explanation": "Tuleb leida ebastabiilsuse põhjus: ajastus, andmed või sõltuvused.",
      "hint": "Mõtle põhjusele, mitte sümptomi peitmisele."
    },
    {
      "level": 3,
      "question": "Analüüsiolukord (Testimise alused): E2E teste on sadu ja unit teste vähe. Milline vastus on kõige täpsem?",
      "options": [
        "see on ideaalne püramiid",
        "tagasiside on aeglane ja habras",
        "väikesed testid pole vajalikud",
        "kõik vead leitakse UI-st"
      ],
      "correctIndex": 1,
      "explanation": "Testipüramiid aitab katta loogikat kiiresti ja jätta rasked vood vähesemateks.",
      "hint": "Mõtle testipüramiidile."
    },
    {
      "level": 3,
      "question": "Analüüsiolukord (Testimise alused): Test sõltub tänasest kuupäevast. Milline vastus on kõige täpsem?",
      "options": [
        "käivita ainult täna",
        "eemalda ootus",
        "fikseeri aeg või sisend",
        "loota kalendrile"
      ],
      "correctIndex": 2,
      "explanation": "Deterministlik test peab andma sama tulemuse samade sisenditega.",
      "hint": "Mõtle ajast sõltuvusele."
    },
    {
      "level": 3,
      "question": "Analüüsiolukord (Testimise alused): Mockitud API testid läbivad, päris API-ga integratsioon ei tööta. Milline vastus on kõige täpsem?",
      "options": [
        "mock tõestab kõike",
        "päris API pole oluline",
        "UI lahendab",
        "lepingut ei kontrollitud"
      ],
      "correctIndex": 3,
      "explanation": "Mock aitab isoleerida, kuid API leping vajab eraldi integratsiooni- või contract-testi.",
      "hint": "Mõtle mocki piirile."
    },
    {
      "level": 3,
      "question": "Analüüsiolukord (Testimise tüübid ja automatiseerimine): Automatiseeritud test sõltub päris välisest AI teenusest. Milline vastus on kõige täpsem?",
      "options": [
        "test on ebastabiilne ja kallis",
        "välised teenused on alati kindlad",
        "mock on keelatud",
        "CI ei vaja determinismi"
      ],
      "correctIndex": 0,
      "explanation": "Väliseid teenuseid tuleks testides mockida või katta eraldi piiratud integratsioonitestiga.",
      "hint": "Mõtle determinismile."
    },
    {
      "level": 3,
      "question": "Analüüsiolukord (Testimise tüübid ja automatiseerimine): Testandmetes kasutatakse päris isikuandmeid. Milline vastus on kõige täpsem?",
      "options": [
        "päris andmed on alati parimad",
        "tekib andmekaitserisk",
        "testid ei leki",
        "JSON peidab andmed"
      ],
      "correctIndex": 1,
      "explanation": "Testandmed peavad olema anonüümsed või sünteetilised.",
      "hint": "Mõtle privaatsusele."
    },
    {
      "level": 3,
      "question": "Analüüsiolukord (Testimise tüübid ja automatiseerimine): E2E test kontrollib kõiki veateate sõnastuse komasid. Milline vastus on kõige täpsem?",
      "options": [
        "see on alati vajalik",
        "UX ei muutu kunagi",
        "test muutub hapraks",
        "kasutaja vajab koma"
      ],
      "correctIndex": 2,
      "explanation": "Sõnastust võib kontrollida olulisel määral, kuid liiga detailne tekstiseos teeb testi ebastabiilseks.",
      "hint": "Mõtle olulisele käitumisele."
    },
    {
      "level": 3,
      "question": "Analüüsiolukord (Testimise tüübid ja automatiseerimine): Kõik testid käivad ainult lokaalselt. Milline vastus on kõige täpsem?",
      "options": [
        "see on piisav koostöös",
        "CI pole vajalik",
        "push parandab vead",
        "tiim ei saa ühist kvaliteedisignaali"
      ],
      "correctIndex": 3,
      "explanation": "CI annab kõigile sama kontrolli ja vähendab 'minu masinas töötab' probleemi.",
      "hint": "Mõtle ühisele keskkonnale."
    },
    {
      "level": 3,
      "question": "Analüüsiolukord (Veebirakenduste loomine klient-server raamistikul): Ärireegel on ainult frontend'is. Milline vastus on kõige täpsem?",
      "options": [
        "seda saab mööda hiilida",
        "UI peitmine on turvakontroll",
        "server ei vaja reegleid",
        "CSS kaitseb"
      ],
      "correctIndex": 0,
      "explanation": "Olulised reeglid peavad olema serveris, frontend pakub mugavust.",
      "hint": "Mõtle autoriteetsele kontrollile."
    },
    {
      "level": 3,
      "question": "Analüüsiolukord (Veebirakenduste loomine klient-server raamistikul): Sessiooni token salvestatakse ebaturvaliselt ja XSS on võimalik. Milline vastus on kõige täpsem?",
      "options": [
        "localStorage on alati turvaline",
        "token võib lekkida",
        "CORS kaitseb XSS-i eest",
        "SQL indeks aitab"
      ],
      "correctIndex": 1,
      "explanation": "Tokeni hoidmine ja XSS kaitse vajavad teadlikku turvalahendust.",
      "hint": "Mõtle ründaja skriptile."
    },
    {
      "level": 3,
      "question": "Analüüsiolukord (Veebirakenduste loomine klient-server raamistikul): Server logib Authorization päise. Milline vastus on kõige täpsem?",
      "options": [
        "logid on alati privaatsed",
        "token peabki logis olema",
        "saladused lekivad logidesse",
        "HTTP 200 peidab selle"
      ],
      "correctIndex": 2,
      "explanation": "Logid võivad olla laiemalt ligipääsetavad, seega saladusi ei logita.",
      "hint": "Mõtle logide elutsüklile."
    },
    {
      "level": 3,
      "question": "Analüüsiolukord (Veebiteenused): Avaliku API vastuse struktuur muutub ilma versioonita. Milline vastus on kõige täpsem?",
      "options": [
        "kliendid kohanevad alati",
        "versioonimine on tarbetu",
        "HTTP parandab",
        "olemasolevad kliendid võivad katki minna"
      ],
      "correctIndex": 3,
      "explanation": "API leping vajab tagurpidi ühilduvust või versioonimist.",
      "hint": "Mõtle teistele tarbijatele."
    },
    {
      "level": 3,
      "question": "Analüüsiolukord (Veebiteenused): Endpoint teeb kõike `action` välja põhjal. Milline vastus on kõige täpsem?",
      "options": [
        "ressursside ja meetodite leping on ebaselge",
        "see on parim REST",
        "HTTP meetodeid pole vaja",
        "JSON nõuab actionit"
      ],
      "correctIndex": 0,
      "explanation": "Selged ressursid ja meetodid muudavad API arusaadavamaks ja testitavamaks.",
      "hint": "Mõtle /users ja /orders stiilis ressurssidele."
    },
    {
      "level": 3,
      "question": "Analüüsiolukord (Veebiteenused): CORS viga brauseris. Milline vastus on kõige täpsem?",
      "options": [
        "andmebaas on katki",
        "server pole ristdomeeni päringut lubanud",
        "HTML on vigane",
        "Git remote puudub"
      ],
      "correctIndex": 1,
      "explanation": "CORS on brauseri turvamehhanism, mida server juhib päistega.",
      "hint": "Mõtle domeenide vahelisele päringule."
    }
  ]
}
